{
  "name":"4.7.0-0.nightly",
  "endOfLife": true,
  "to": "release",
  "message": "This release contains OSBS official image builds of all code in release-4.7 (master) branches, and is updated after those builds are synced to quay.io.",
  "mirrorPrefix": "4.7-art-latest",
  "expires":"126h",
  "maxUnreadyReleases": 1,
  "minCreationIntervalSeconds": 21600,
  "referenceMode": "source",
  "pullSecretName": "source",
  "overrideCLIImage": "image-registry.openshift-image-registry.svc:5000/ocp/4.11-art-latest:cli",
  "check":{
    "OCP and Origin images should match": {
      "consistentImages":{"parent":"4.7.0-0.ci"}
    }
  },
  "publish":{
    "tag":{"tagRef":{"name":"4.7"}},
    "issues": {
      "verifyIssues": {
        "previousReleaseTag": {
          "namespace": "ocp",
          "name": "release",
          "tag": "4.7.0-rc.0"
        }
      }
    }
  },
  "verify":{
    "aws":{
      "maxRetries": 3,
      "prowJob":{"name":"periodic-ci-openshift-release-master-nightly-4.7-e2e-aws"}
    },
    "aws-serial":{
      "maxRetries": 3,
      "prowJob":{"name":"periodic-ci-openshift-release-master-nightly-4.7-e2e-aws-serial"}
    },
    "azure":{
      "optional":true,
      "prowJob":{"name":"periodic-ci-openshift-release-master-nightly-4.7-e2e-azure"}
    },
    "gcp":{
      "optional":true,
      "prowJob":{"name":"periodic-ci-openshift-release-master-nightly-4.7-e2e-gcp"}
    },
    "gcp-rt":{
      "optional":true,
      "prowJob":{"name":"periodic-ci-openshift-release-master-nightly-4.7-e2e-gcp-rt"}
    },
    "metal-ipi": {
      "optional":true,
      "prowJob":{"name":"periodic-ci-openshift-release-master-nightly-4.7-e2e-metal-ipi"}
    },
    "metal-ipi-upgrade":{
      "upgrade":true,
      "optional":true,
      "prowJob":{"name":"periodic-ci-openshift-release-master-nightly-4.7-e2e-metal-ipi-upgrade"}
    },
    "metal-ipi-ovn-ipv6": {
      "optional":true,
      "prowJob":{"name":"periodic-ci-openshift-release-master-nightly-4.7-e2e-metal-ipi-ovn-ipv6"}
    },
    "metal-ipi-ovn-dualstack": {
      "optional":true,
      "prowJob":{"name":"periodic-ci-openshift-release-master-nightly-4.7-e2e-metal-ipi-ovn-dualstack"}
    },
    "metal-ipi-virtualmedia": {
      "optional": true,
      "prowJob":{"name":"periodic-ci-openshift-release-master-nightly-4.7-e2e-metal-ipi-virtualmedia"}
    },
    "vsphere-upi":{
      "optional": true,
      "prowJob":{"name":"periodic-ci-openshift-release-master-nightly-4.7-e2e-vsphere-upi"}
    },
    "vsphere":{
      "optional": true,
      "prowJob":{"name":"periodic-ci-openshift-release-master-nightly-4.7-e2e-vsphere"}
    },
    "vsphere-upi-serial":{
      "optional": true,
      "prowJob":{"name":"periodic-ci-openshift-release-master-nightly-4.7-e2e-vsphere-upi-serial"}
    },
    "vsphere-serial":{
      "optional": true,
      "prowJob":{"name":"periodic-ci-openshift-release-master-nightly-4.7-e2e-vsphere-serial"}
    },
    "aws-console":{
      "optional":true,
      "prowJob":{"name":"periodic-ci-openshift-release-master-nightly-4.7-console-aws"}
    },
    "upgrade":{
      "upgrade":true,
      "optional":true,
      "prowJob":{"name":"periodic-ci-openshift-release-master-nightly-4.7-e2e-aws-upgrade"}
    },
    "upgrade-minor":{
      "upgrade":true,
      "upgradeFrom": "PreviousMinor",
      "optional":true,
      "prowJob":{"name":"periodic-ci-openshift-release-master-nightly-4.7-upgrade-from-stable-4.6-e2e-aws-upgrade"}
    },
    "aws-fips":{
      "optional":true,
      "prowJob":{"name":"periodic-ci-openshift-release-master-nightly-4.7-e2e-aws-fips"}
    },
    "aws-ovn":{
      "optional":true,
      "prowJob":{"name":"periodic-ci-openshift-release-master-ci-4.7-e2e-aws-ovn"}
    },
    "gcp-ovn":{
      "optional":true,
      "prowJob":{"name":"periodic-ci-openshift-release-master-ci-4.7-e2e-gcp-ovn"}
    },
    "azure-ovn":{
      "optional":true,
      "prowJob":{"name":"periodic-ci-openshift-release-master-ci-4.7-e2e-azure-ovn"}
    },
    "ovirt":{
      "optional":true,
      "prowJob":{"name":"periodic-ci-openshift-release-master-nightly-4.7-e2e-ovirt"}
    },
    "proxy":{
      "optional":true,
      "prowJob":{"name":"periodic-ci-openshift-release-master-nightly-4.7-e2e-aws-proxy"}
    }
  }
}
