{
    "endOfLife": true,
    "expires": "168h",
    "message": "<!-- GENERATED FROM PUBLIC ANNOTATION CONFIG - DO NOT EDIT. -->This release contains OSBS official image builds of all arm64 code in release-4.9 (master) branches, and is updated after those builds are synced to quay.io.",
    "mirrorPrefix": "4.9-art-latest-arm64-priv",
    "name": "4.9.0-0.nightly-arm64-priv",
    "overrideCLIImage": "image-registry.openshift-image-registry.svc:5000/ocp/4.11-art-latest:cli",
    "pullSecretName": "source",
    "referenceMode": "source",
    "to": "release-arm64-priv",
    "verify": {
        "aws-arm64": {
            "disabled": true,
            "optional": true,
            "prowJob": {
                "name": "periodic-ci-openshift-multiarch-master-nightly-4.9-ocp-e2e-aws-arm64-priv"
            }
        }
    }
}